noiseestimator/__init__.py
noiseestimator/_version.py
noiseestimator/noiseestimator.py
noiseestimator/py.typed
noiseestimator/tests/__init__.py
noiseestimator/tests/test_noiseestimator.py
noiseestimator-0.0.1.dist-info/LICENSE
noiseestimator-0.0.1.dist-info/METADATA
noiseestimator-0.0.1.dist-info/WHEEL
noiseestimator-0.0.1.dist-info/top_level.txt
noiseestimator-0.0.1.dist-info/RECORD
